Workbook

Sheet Master Keywords
A1: Cluster | B1: Keyword | C1: PH Volume/mo | D1: KD | E1: Intent | F1: Recommended Page Type | G1: Suggested URL | H1: Opportunity Score | I1: Priority | J1: Source
A2: Motorcycle Prices & Models | B2: aerox v3 price philippines | C2: 41000 | D2: 0 | E2: Commercial | F2: Model price/spec page | G2: /motorcycles/aerox-v3-price-philippines/ | H2: =ROUND(MIN(100,LOG10(C2+1)*18+(10-D2)*2+IF(OR(E2="Commercial",E2="Informational / Transactional"),12,5)),0) | I2: =IF(H2>=85,"P1",IF(H2>=70,"P2","P3")) | J2: https://ahrefs.com/keywords-explorer
A3: Motorcycle Prices & Models | B3: nmax price philippines | C3: 23000 | D3: 0 | E3: Commercial | F3: Model price/spec page | G3: /motorcycles/nmax-price-philippines/ | H3: =ROUND(MIN(100,LOG10(C3+1)*18+(10-D3)*2+IF(OR(E3="Commercial",E3="Informational / Transactional"),12,5)),0) | I3: =IF(H3>=85,"P1",IF(H3>=70,"P2","P3")) | J3: https://ahrefs.com/keywords-explorer
A4: Motorcycle Prices & Models | B4: aerox v2 price philippines | C4: 20000 | D4: 8 | E4: Commercial | F4: Model price/spec page | G4: /motorcycles/aerox-v2-price-philippines/ | H4: =ROUND(MIN(100,LOG10(C4+1)*18+(10-D4)*2+IF(OR(E4="Commercial",E4="Informational / Transactional"),12,5)),0) | I4: =IF(H4>=85,"P1",IF(H4>=70,"P2","P3")) | J4: https://ahrefs.com/keywords-explorer
A5: Motorcycle Prices & Models | B5: aerox price philippines | C5: 14000 | D5: 8 | E5: Commercial | F5: Model price/spec page | G5: /motorcycles/aerox-price-philippines/ | H5: =ROUND(MIN(100,LOG10(C5+1)*18+(10-D5)*2+IF(OR(E5="Commercial",E5="Informational / Transactional"),12,5)),0) | I5: =IF(H5>=85,"P1",IF(H5>=70,"P2","P3")) | J5: https://ahrefs.com/keywords-explorer
A6: Motorcycle Prices & Models | B6: nmax v3 price philippines | C6: 14000 | D6: 0 | E6: Commercial | F6: Model price/spec page | G6: /motorcycles/nmax-v3-price-philippines/ | H6: =ROUND(MIN(100,LOG10(C6+1)*18+(10-D6)*2+IF(OR(E6="Commercial",E6="Informational / Transactional"),12,5)),0) | I6: =IF(H6>=85,"P1",IF(H6>=70,"P2","P3")) | J6: https://ahrefs.com/keywords-explorer
A7: Motorcycle Prices & Models | B7: adv 160 price philippines | C7: 13000 | D7: 0 | E7: Commercial | F7: Model price/spec page | G7: /motorcycles/adv-160-price-philippines/ | H7: =ROUND(MIN(100,LOG10(C7+1)*18+(10-D7)*2+IF(OR(E7="Commercial",E7="Informational / Transactional"),12,5)),0) | I7: =IF(H7>=85,"P1",IF(H7>=70,"P2","P3")) | J7: https://ahrefs.com/keywords-explorer
A8: Motorcycle Prices & Models | B8: honda adv 160 price philippines | C8: 13000 | D8: 0 | E8: Commercial | F8: Model price/spec page | G8: /motorcycles/honda-adv-160-price-philippines/ | H8: =ROUND(MIN(100,LOG10(C8+1)*18+(10-D8)*2+IF(OR(E8="Commercial",E8="Informational / Transactional"),12,5)),0) | I8: =IF(H8>=85,"P1",IF(H8>=70,"P2","P3")) | J8: https://ahrefs.com/keywords-explorer
A9: Motorcycle Prices & Models | B9: nmax v2 price philippines | C9: 13000 | D9: 0 | E9: Commercial | F9: Model price/spec page | G9: /motorcycles/nmax-v2-price-philippines/ | H9: =ROUND(MIN(100,LOG10(C9+1)*18+(10-D9)*2+IF(OR(E9="Commercial",E9="Informational / Transactional"),12,5)),0) | I9: =IF(H9>=85,"P1",IF(H9>=70,"P2","P3")) | J9: https://ahrefs.com/keywords-explorer
A10: Motorcycle Prices & Models | B10: honda click 160 price philippines | C10: 11000 | D10: 0 | E10: Commercial | F10: Model price/spec page | G10: /motorcycles/honda-click-160-price-philippines/ | H10: =ROUND(MIN(100,LOG10(C10+1)*18+(10-D10)*2+IF(OR(E10="Commercial",E10="Informational / Transactional"),12,5)),0) | I10: =IF(H10>=85,"P1",IF(H10>=70,"P2","P3")) | J10: https://ahrefs.com/keywords-explorer
A11: Motorcycle Prices & Models | B11: pcx price philippines | C11: 8300 | D11: 0 | E11: Commercial | F11: Model price/spec page | G11: /motorcycles/pcx-price-philippines/ | H11: =ROUND(MIN(100,LOG10(C11+1)*18+(10-D11)*2+IF(OR(E11="Commercial",E11="Informational / Transactional"),12,5)),0) | I11: =IF(H11>=85,"P1",IF(H11>=70,"P2","P3")) | J11: https://ahrefs.com/keywords-explorer
A12: Motorcycle Prices & Models | B12: fazzio price philippines | C12: 7600 | D12: 0 | E12: Commercial | F12: Model price/spec page | G12: /motorcycles/fazzio-price-philippines/ | H12: =ROUND(MIN(100,LOG10(C12+1)*18+(10-D12)*2+IF(OR(E12="Commercial",E12="Informational / Transactional"),12,5)),0) | I12: =IF(H12>=85,"P1",IF(H12>=70,"P2","P3")) | J12: https://ahrefs.com/keywords-explorer
A13: Motorcycle Prices & Models | B13: adv price philippines | C13: 6500 | D13: 0 | E13: Commercial | F13: Model price/spec page | G13: /motorcycles/adv-price-philippines/ | H13: =ROUND(MIN(100,LOG10(C13+1)*18+(10-D13)*2+IF(OR(E13="Commercial",E13="Informational / Transactional"),12,5)),0) | I13: =IF(H13>=85,"P1",IF(H13>=70,"P2","P3")) | J13: https://ahrefs.com/keywords-explorer
... A394: Model Specs & Compatibility | B394: motorcycle wheel parts | C394: 60 | D394: 1 | E394: Informational | F394: Spec / compatibility page | G394: /specs/motorcycle-wheel-parts/ | H394: =ROUND(MIN(100,LOG10(C394+1)*18+(10-D394)*2+IF(OR(E394="Commercial",E394="Informational / Transactional"),12,5)),0) | I394: =IF(H394>=85,"P1",IF(H394>=70,"P2","P3")) | J394: https://ahrefs.com/keywords-explorer

Sheet Topic Map
A1: PH Motorcycle SEO Topic Map
A2: Ahrefs Philippines keyword set, focused on KD 0–10. Volumes are monthly estimates and should be refreshed before launch.
A4: Cluster | B4: Keyword Count | C4: Total PH Volume | D4: Avg KD | E4: Primary Monetization | F4: Core Template | G4: Launch Phase | H4: Notes
A5: Motorcycle Prices & Models | B5: =COUNTIF('Master Keywords'!$A:$A,A5) | C5: =SUMIF('Master Keywords'!$A:$A,A5,'Master Keywords'!$C:$C) | D5: =IFERROR(AVERAGEIF('Master Keywords'!$A:$A,A5,'Master Keywords'!$D:$D),0) | E5: Dealer leads / financing / ads | F5: Model price + specs | G5: Phase 1 | H5: Traffic anchor. Build accurate model database first.
A6: Tires & Fitment | B6: =COUNTIF('Master Keywords'!$A:$A,A6) | C6: =SUMIF('Master Keywords'!$A:$A,A6,'Master Keywords'!$C:$C) | D6: =IFERROR(AVERAGEIF('Master Keywords'!$A:$A,A6,'Master Keywords'!$D:$D),0) | E6: Tire affiliates / local leads | F6: Model tire-fitment page | G6: Phase 1 | H6: Excellent pSEO fit: model × tire size × front/rear × pressure.
A7: Helmets & Safety | B7: =COUNTIF('Master Keywords'!$A:$A,A7) | C7: =SUMIF('Master Keywords'!$A:$A,A7,'Master Keywords'!$C:$C) | D7: =IFERROR(AVERAGEIF('Master Keywords'!$A:$A,A7,'Master Keywords'!$D:$D),0) | E7: Affiliate / ecommerce / sponsors | F7: Helmet brand + price hub | G7: Phase 1 | H7: Large PH demand and many KD 0 terms.
A8: Accessories & Riding Gear | B8: =COUNTIF('Master Keywords'!$A:$A,A8) | C8: =SUMIF('Master Keywords'!$A:$A,A8,'Master Keywords'!$C:$C) | D8: =IFERROR(AVERAGEIF('Master Keywords'!$A:$A,A8,'Master Keywords'!$D:$D),0) | E8: Affiliate / ecommerce | F8: Model-accessory compatibility | G8: Phase 2 | H8: Top boxes, intercoms, phone mounts, rain gear, jackets, gloves.
A9: Maintenance & Parts | B9: =COUNTIF('Master Keywords'!$A:$A,A9) | C9: =SUMIF('Master Keywords'!$A:$A,A9,'Master Keywords'!$C:$C) | D9: =IFERROR(AVERAGEIF('Master Keywords'!$A:$A,A9,'Master Keywords'!$D:$D),0) | E9: Parts affiliate / service leads / ads | F9: Maintenance guide + part hub | G9: Phase 2 | H9: Evergreen repeat traffic; supports model authority.
A10: Ownership, LTO & Insurance | B10: =COUNTIF('Master Keywords'!$A:$A,A10) | C10: =SUMIF('Master Keywords'!$A:$A,A10,'Master Keywords'!$C:$C) | D10: =IFERROR(AVERAGEIF('Master Keywords'!$A:$A,A10,'Master Keywords'!$D:$D),0) | E10: Insurance leads / ads | F10: LTO process + fee page | G10: Phase 2 | H10: High utility. Must cite official sources and maintain freshness.
A11: Comparisons & Buying Guides | B11: =COUNTIF('Master Keywords'!$A:$A,A11) | C11: =SUMIF('Master Keywords'!$A:$A,A11,'Master Keywords'!$C:$C) | D11: =IFERROR(AVERAGEIF('Master Keywords'!$A:$A,A11,'Master Keywords'!$D:$D),0) | E11: Dealer leads / affiliate | F11: Comparison / best-of | G11: Phase 1 | H11: Strong mid-funnel content and internal-link bridge.
A12: Financing & Installments | B12: =COUNTIF('Master Keywords'!$A:$A,A12) | C12: =SUMIF('Master Keywords'!$A:$A,A12,'Master Keywords'!$C:$C) | D12: =IFERROR(AVERAGEIF('Master Keywords'!$A:$A,A12,'Master Keywords'!$D:$D),0) | E12: Finance/dealer leads | F12: Loan/installment calculator | G12: Phase 1 | H12: Highest commercial value even at lower volume.
A13: Local Shops & Dealers | B13: =COUNTIF('Master Keywords'!$A:$A,A13) | C13: =SUMIF('Master Keywords'!$A:$A,A13,'Master Keywords'!$C:$C) | D13: =IFERROR(AVERAGEIF('Master Keywords'!$A:$A,A13,'Master Keywords'!$D:$D),0) | E13: Dealer/service leads | F13: City/category directory | G13: Phase 3 | H13: Useful after the main model database has authority.
A14: Model Specs & Compatibility | B14: =COUNTIF('Master Keywords'!$A:$A,A14) | C14: =SUMIF('Master Keywords'!$A:$A,A14,'Master Keywords'!$C:$C) | D14: =IFERROR(AVERAGEIF('Master Keywords'!$A:$A,A14,'Master Keywords'!$D:$D),0) | E14: Affiliate / ads | F14: Spec database page | G14: Phase 2 | H14: Programmatic support pages from structured specs.

Sheet Volume-First Roadmap
A1: MotoIndex PH — Volume-First Build Roadmap
A2: Built from the 393-keyword Philippines dataset plus a current MotoIndex route/data review. Search volumes are Ahrefs estimates; grouped volumes overlap and are not unique visitors. | N2: Scoring controls
N3: Volume weight | O3: 0.6
A4: Total keyword volume/mo | D4: Prices & models/mo | G4: Helmets & safety/mo | J4: Tires & fitment/mo | N4: KD weight | O4: 0.15
A5: 469610 | D5: 269660 | G5: 120700 | J5: 18000 | N5: Monetization weight | O5: 0.15
N6: Effort weight | O6: 0.1
A7: Volume Rank | B7: Build target | C7: Cluster | D7: Addressable keyword volume/mo | E7: Primary KD | F7: Current MotoIndex status | G7: Recommended action | H7: Target URL | I7: Monetization | J7: Effort | K7: Priority Score | L7: Phase
A8: 1 | B8: Yamaha Aerox V3 price landing | C8: Motorcycle Prices & Models | D8: 43000 | E8: 0 | F8: Shipped v2.4.0 | G8: Maintain price freshness and Search Console CTR; do not create alias pages. | H8: /motorcycles/yamaha/aerox-v3/price/ | I8: High | J8: Low | K8: =ROUND($O$3*(LOG10(D8+1)/LOG10(MAX($D$8:$D$27)+1)*100)+$O$4*((10-MIN(E8,10))*10)+$O$5*IF(I8="High",100,IF(I8="Medium",60,30))+$O$6*IF(J8="Low",100,IF(J8="Medium",60,30)),0) | L8: P0
A9: 2 | B9: Honda ADV 160 price landing | C9: Motorcycle Prices & Models | D9: 28800 | E9: 0 | F9: Shipped v2.4.0 | G9: Maintain source freshness and strengthen dealer/finance conversion when real partners exist. | H9: /motorcycles/honda/adv-160/price/ | I9: High | J9: Low | K9: =ROUND($O$3*(LOG10(D9+1)/LOG10(MAX($D$8:$D$27)+1)*100)+$O$4*((10-MIN(E9,10))*10)+$O$5*IF(I9="High",100,IF(I9="Medium",60,30))+$O$6*IF(J9="Low",100,IF(J9="Medium",60,30)),0) | L9: P0
A10: 3 | B10: Yamaha NMAX price / family hub | C10: Motorcycle Prices & Models | D10: 25800 | E10: 0 | F10: Shipped v2.4.0 | G10: Family hub is live; monitor generic NMAX query cannibalization across generation pages. | H10: /motorcycles/yamaha/nmax/ | I10: High | J10: Low | K10: =ROUND($O$3*(LOG10(D10+1)/LOG10(MAX($D$8:$D$27)+1)*100)+$O$4*((10-MIN(E10,10))*10)+$O$5*IF(I10="High",100,IF(I10="Medium",60,30))+$O$6*IF(J10="Low",100,IF(J10="Medium",60,30)),0) | L10: P0
A11: 4 | B11: Yamaha Aerox V2 price landing | C11: Motorcycle Prices & Models | D11: 20000 | E11: 8 | F11: Shipped v2.4.0 | G11: Generation page is live; keep used/new intent linked rather than duplicating pages. | H11: /motorcycles/yamaha/aerox-v2/price/ | I11: High | J11: Low | K11: =ROUND($O$3*(LOG10(D11+1)/LOG10(MAX($D$8:$D$27)+1)*100)+$O$4*((10-MIN(E11,10))*10)+$O$5*IF(I11="High",100,IF(I11="Medium",60,30))+$O$6*IF(J11="Low",100,IF(J11="Medium",60,30)),0) | L11: P0
A12: 5 | B12: Yamaha Aerox family price hub | C12: Motorcycle Prices & Models | D12: 18100 | E12: 8 | F12: Shipped v2.4.0 | G12: Family hub is live; keep V2/V3 targeting separate and canonical. | H12: /motorcycles/yamaha/aerox/ | I12: High | J12: Low | K12: =ROUND($O$3*(LOG10(D12+1)/LOG10(MAX($D$8:$D$27)+1)*100)+$O$4*((10-MIN(E12,10))*10)+$O$5*IF(I12="High",100,IF(I12="Medium",60,30))+$O$6*IF(J12="Low",100,IF(J12="Medium",60,30)),0) | L12: P0
A13: 6 | B13: Honda PCX / PCX 160 price hub | C13: Motorcycle Prices & Models | D13: 16700 | E13: 0 | F13: Shipped v2.4.0 | G13: PCX/PCX160 price coverage is live; refresh current price observations. | H13: /motorcycles/honda/pcx-160/price/ | I13: High | J13: Low | K13: =ROUND($O$3*(LOG10(D13+1)/LOG10(MAX($D$8:$D$27)+1)*100)+$O$4*((10-MIN(E13,10))*10)+$O$5*IF(I13="High",100,IF(I13="Medium",60,30))+$O$6*IF(J13="Low",100,IF(J13="Medium",60,30)),0) | L13: P0
A14: 7 | B14: Tire fitment page expansion | C14: Tires & Fitment | D14: 16250 | E14: 0 | F14: Shipped v2.4.1 | G14: High-volume tire family hubs and model tire pages are live; expand only with verified fitment data. | H14: /tires | I14: High | J14: Medium | K14: =ROUND($O$3*(LOG10(D14+1)/LOG10(MAX($D$8:$D$27)+1)*100)+$O$4*((10-MIN(E14,10))*10)+$O$5*IF(I14="High",100,IF(I14="Medium",60,30))+$O$6*IF(J14="Low",100,IF(J14="Medium",60,30)),0) | L14: P1
A15: 8 | B15: Honda Click 160 price landing | C15: Motorcycle Prices & Models | D15: 16000 | E15: 0 | F15: Shipped v2.4.0 | G15: Click 160 price intent is covered; maintain variants and dated prices. | H15: /motorcycles/honda/click-160/price/ | I15: High | J15: Low | K15: =ROUND($O$3*(LOG10(D15+1)/LOG10(MAX($D$8:$D$27)+1)*100)+$O$4*((10-MIN(E15,10))*10)+$O$5*IF(I15="High",100,IF(I15="Medium",60,30))+$O$6*IF(J15="Low",100,IF(J15="Medium",60,30)),0) | L15: P0
A16: 9 | B16: EVO helmet brand + price hub | C16: Helmets & Safety | D16: 15700 | E16: 0 | F16: Shipped / deepen | G16: EVO brand hub is live; add products only when source-backed. | H16: /gear/helmets/evo/ | I16: High | J16: Medium | K16: =ROUND($O$3*(LOG10(D16+1)/LOG10(MAX($D$8:$D$27)+1)*100)+$O$4*((10-MIN(E16,10))*10)+$O$5*IF(I16="High",100,IF(I16="Medium",60,30))+$O$6*IF(J16="Low",100,IF(J16="Medium",60,30)),0) | L16: P1
A17: 10 | B17: Yamaha NMAX V3 price landing | C17: Motorcycle Prices & Models | D17: 14800 | E17: 0 | F17: Shipped v2.4.0 | G17: NMAX V3 price page is live; maintain current source date. | H17: /motorcycles/yamaha/nmax-v3/price/ | I17: High | J17: Low | K17: =ROUND($O$3*(LOG10(D17+1)/LOG10(MAX($D$8:$D$27)+1)*100)+$O$4*((10-MIN(E17,10))*10)+$O$5*IF(I17="High",100,IF(I17="Medium",60,30))+$O$6*IF(J17="Low",100,IF(J17="Medium",60,30)),0) | L17: P0
A18: 11 | B18: Spyder helmet brand + price hub | C18: Helmets & Safety | D18: 13200 | E18: 0 | F18: Shipped / deepen | G18: Spyder brand hub is live; improve product breadth when verified. | H18: /gear/helmets/spyder/ | I18: High | J18: Medium | K18: =ROUND($O$3*(LOG10(D18+1)/LOG10(MAX($D$8:$D$27)+1)*100)+$O$4*((10-MIN(E18,10))*10)+$O$5*IF(I18="High",100,IF(I18="Medium",60,30))+$O$6*IF(J18="Low",100,IF(J18="Medium",60,30)),0) | L18: P1
A19: 12 | B19: KYT helmet brand hub | C19: Helmets & Safety | D19: 11000 | E19: 0 | F19: Shipped / deepen | G19: KYT brand hub is live; improve product breadth when verified. | H19: /gear/helmets/kyt/ | I19: High | J19: Medium | K19: =ROUND($O$3*(LOG10(D19+1)/LOG10(MAX($D$8:$D$27)+1)*100)+$O$4*((10-MIN(E19,10))*10)+$O$5*IF(I19="High",100,IF(I19="Medium",60,30))+$O$6*IF(J19="Low",100,IF(J19="Medium",60,30)),0) | L19: P1
... A27: 20 | B27: Shoei helmet brand + price hub | C27: Helmets & Safety | D27: 5300 | E27: 5 | F27: Shipped / monitor | G27: Shoei brand page exists; expand PH product depth only when source-backed. | H27: /gear/helmets/shoei/ | I27: High | J27: Medium | K27: =ROUND($O$3*(LOG10(D27+1)/LOG10(MAX($D$8:$D$27)+1)*100)+$O$4*((10-MIN(E27,10))*10)+$O$5*IF(I27="High",100,IF(I27="Medium",60,30))+$O$6*IF(J27="Low",100,IF(J27="Medium",60,30)),0) | L27: P2
A29: Execution Plan
A30: Phase 0 — Traffic capture | B30: Optimize the already-built price winners first: Aerox V3, ADV 160, NMAX family/V3, Aerox V2/family, PCX 160 and Click 160. Focus on canonicalization, 2026 freshness, variant pricing, schema and internal links. | I30: ~169K+ query-set volume represented by the first price targets; overlap means this is not unique traffic.
A31: Phase 1 — Helmet monetization | B31: Expand EVO, Spyder, KYT, Gille, SEC and the generic helmet hub. Add verified product depth, current PH pricing, certifications and affiliate CTAs. | I31: Largest monetizable cluster: 120.7K/mo across the full helmet dataset.
A32: Phase 2 — Fitment + accessories | B32: Scale tire-size pages and build the top-box buying/fitment hub. Both can monetize through product matching while strengthening model pages. | I32: Tires 18K/mo cluster; top-box keyword set ~8.7K/mo.
A33: Phase 3 — Quick-win authority | B33: Publish the DL Code B motorcycle guide with current LTO sourcing and connect it to registration/ownership tools. | I33: ~5.75K/mo query set, KD 0; unusually high volume for a single low-effort guide.
A34: Phase 4 — Expand missing commerce brands | B34: Add missing helmet brands in volume order: Zebra, HNJ, Shark, MT, Bell. Do not publish brand pages until real product/price records exist. | I34: Adds another ~12.7K/mo of explicit brand demand from the workbook.
A35: Phase 5 — Used-market layer | B35: After the higher-volume work, build used-price intelligence / repo hub / buyer trust, then listings. | I35: Fresh Ahrefs PH checks: repo motorcycle ~800/mo; deed of sale for motorcycle ~800/mo; second hand motorcycle for sale ~300/mo; second hand motorcycle ~250/mo.
A37: Next 5 Missing / Underbuilt Helmet Brand Gaps
A38: Rank | B38: Brand build | C38: Workbook volume/mo | D38: KD | E38: Current status | F38: Recommended next step | G38: Target URL | H38: Monetization
A39: 1 | B39: Zebra helmet hub | C39: 4000 | D39: 0 | E39: Brand not found in current helmet catalog | F39: Source 3+ real models, PH prices, certification and images before indexing. | G39: /gear/helmets/zebra/ | H39: High
A40: 2 | B40: HNJ helmet hub | C40: 2700 | D40: 0 | E40: Brand not found in current helmet catalog | F40: Build verified catalog first; then publish brand/price page. | G40: /gear/helmets/hnj/ | H40: High
A41: 3 | B41: Shark helmet hub + price | C41: 2400 | D41: 0 | E41: Brand not found in current helmet catalog | F41: Add current PH-available models and price references; avoid thin brand page. | G41: /gear/helmets/shark/ | H41: High
A42: 4 | B42: MT helmet hub | C42: 1900 | D42: 0 | E42: Brand not found in current helmet catalog | F42: Add verified catalog and current price bands before indexing. | G42: /gear/helmets/mt/ | H42: High
A43: 5 | B43: Bell helmet hub | C43: 1700 | D43: 7 | E43: Brand not found in current helmet catalog | F43: Lower priority due KD 7; build only after sufficient product depth. | G43: /gear/helmets/bell/ | H43: High
A45: How to Use This Roadmap
A46: Volume first, not traffic forecast | B46: Addressable keyword volume is search-query volume, not expected visits and not unique users. Related queries can overlap.
A47: Avoid cannibalization | B47: Where two keywords express the same intent (for example “adv 160 price philippines” and “honda adv 160 price philippines”), use one canonical page.
A48: Do not index thin pages | B48: New brand/model/category pages should only go live when data is verified and the page answers a distinct user need.
A49: Revenue overlay | B49: Prioritize affiliate-enabled helmet/accessory pages once verified links are configured; price pages mainly drive discovery and dealer/finance intent.
A50: Sources | B50: Workbook keyword metrics: https://ahrefs.com/keywords-explorer ; current MotoIndex status: local v2.3.1 patched project review on 2026-08-26. Used-market spot checks: Ahrefs Keywords Explorer PH, 2026-08-26.

Sheet SEO Roadmap v2.4.5
A1: MotoIndex PH — Current SEO Roadmap after v2.4.5
A2: Focus has shifted from price/helmet/tire coverage (mostly shipped) to registration intent, evergreen maintenance/parts, exact model service depth, and only then verified local discovery.
A4: Dataset PH volume/mo | C4: Prices & models/mo | E4: Helmets & safety/mo | G4: Maintenance & parts/mo | I4: Ownership/LTO/mo | K4: Tires & fitment/mo
A5: 469610 | C5: 269660 | E5: 120700 | G5: 13570 | I5: 14520 | K5: 18000
A7: Rank | B7: Build target | C7: Primary keyword / cluster | D7: Addressable PH volume/mo | E7: KD | F7: Current status | G7: Recommended action | H7: Target URL | I7: Monetization | J7: Effort | K7: Priority score | L7: Release | M7: Why now | N7: Source
A8: 1 | B8: Motorcycle registration renewal refresh | C8: motorcycle registration + renewal cluster | D8: =SUMIF('Master Keywords'!$B:$B,"*motorcycle registration*",'Master Keywords'!$C:$C) | E8: 0 | F8: Improved v2.4.5 | G8: Consolidate requirements, LTMS/online intent, fee questions and renewal timing on the existing canonical guide. Keep current LTO sources and calculator linked. | H8: /ownership/registration-renewal | I8: Medium | J8: Low | K8: =ROUND(0.55*(IF(D8>0,LOG10(D8+1)/LOG10(MAX($D$8:$D$21)+1)*100,35))+0.15*((10-MIN(E8,10))*10)+0.2*IF(I8="High",100,IF(I8="Medium",65,35))+0.1*IF(J8="Low",100,IF(J8="Medium",60,30)),0) | L8: v2.4.5 | M8: Largest remaining low-KD ownership cluster; existing page can win without a new data model. | N8: https://ahrefs.com/keywords-explorer
A9: 2 | B9: Helmet brands comparison intent | C9: helmet brand / helmet brands / best helmet brands | D9: =SUMIF('Master Keywords'!$B:$B,"*helmet brand*",'Master Keywords'!$C:$C) | E9: 0 | F9: Improved v2.4.5 | G9: Use the existing brand-comparison page for generic and “best” intent without publishing a fake safety ranking. | H9: /gear/helmets/brands | I9: High | J9: Low | K9: =ROUND(0.55*(IF(D9>0,LOG10(D9+1)/LOG10(MAX($D$8:$D$21)+1)*100,35))+0.15*((10-MIN(E9,10))*10)+0.2*IF(I9="High",100,IF(I9="Medium",65,35))+0.1*IF(J9="Low",100,IF(J9="Medium",60,30)),0) | L9: v2.4.5 | M9: High commercial intent and the product catalog already exists. | N9: https://ahrefs.com/keywords-explorer
A10: 3 | B10: Motorcycle battery guide | C10: motorcycle battery cluster | D10: =SUMIF('Master Keywords'!$B:$B,"*motorcycle battery*",'Master Keywords'!$C:$C) | E10: 0 | F10: Built v2.4.5 | G10: Own battery fitment, charging, lifespan and replacement-intent queries; add real battery products only after model fitment is verified. | H10: /maintenance/motorcycle-battery | I10: High | J10: Low | K10: =ROUND(0.55*(IF(D10>0,LOG10(D10+1)/LOG10(MAX($D$8:$D$21)+1)*100,35))+0.15*((10-MIN(E10,10))*10)+0.2*IF(I10="High",100,IF(I10="Medium",65,35))+0.1*IF(J10="Low",100,IF(J10="Medium",60,30)),0) | L10: v2.4.5 | M10: Evergreen commercial maintenance intent with KD 0. | N10: https://ahrefs.com/keywords-explorer
A11: 4 | B11: Parts of a motorcycle guide | C11: parts of motorcycle | D11: =SUMIF('Master Keywords'!$B:$B,"parts of motorcycle",'Master Keywords'!$C:$C) | E11: 7 | F11: Built v2.4.5 | G11: Use as the broad educational hub that links drivetrain, battery, oil, coolant, tires and accessories. | H11: /maintenance/parts-of-motorcycle | I11: Low | J11: Low | K11: =ROUND(0.55*(IF(D11>0,LOG10(D11+1)/LOG10(MAX($D$8:$D$21)+1)*100,35))+0.15*((10-MIN(E11,10))*10)+0.2*IF(I11="High",100,IF(I11="Medium",65,35))+0.1*IF(J11="Low",100,IF(J11="Medium",60,30)),0) | L11: v2.4.5 | M11: Largest single unserved informational maintenance query. | N11: https://ahrefs.com/keywords-explorer
A12: 5 | B12: Motorcycle insurance intent refresh | C12: motorcycle insurance cluster | D12: =SUMIF('Master Keywords'!$B:$B,"*motorcycle insurance*",'Master Keywords'!$C:$C) | E12: 0 | F12: Existing guide + calculator | G12: Keep CTPL/comprehensive explanations regulator-sourced; improve internal links and add provider comparison only with current regulated product data. | H12: /ownership/motorcycle-insurance | I12: High | J12: Low | K12: =ROUND(0.55*(IF(D12>0,LOG10(D12+1)/LOG10(MAX($D$8:$D$21)+1)*100,35))+0.15*((10-MIN(E12,10))*10)+0.2*IF(I12="High",100,IF(I12="Medium",65,35))+0.1*IF(J12="Low",100,IF(J12="Medium",60,30)),0) | L12: v2.4.6 | M12: Strong CPC/commercial intent; current foundation is already credible. | N12: https://ahrefs.com/keywords-explorer
A13: 6 | B13: Motorcycle change-oil guide | C13: change oil motorcycle cluster | D13: =SUMIF('Master Keywords'!$B:$B,"*change oil*",'Master Keywords'!$C:$C) | E13: 2 | F13: Built v2.4.5 | G13: Target interval, oil-type and scooter final-drive questions while refusing one-size-fits-all kilometer advice. | H13: /maintenance/change-oil-motorcycle | I13: Medium | J13: Low | K13: =ROUND(0.55*(IF(D13>0,LOG10(D13+1)/LOG10(MAX($D$8:$D$21)+1)*100,35))+0.15*((10-MIN(E13,10))*10)+0.2*IF(I13="High",100,IF(I13="Medium",65,35))+0.1*IF(J13="Low",100,IF(J13="Medium",60,30)),0) | L13: v2.4.5 | M13: Evergreen repeat intent and natural bridge to model maintenance pages. | N13: https://ahrefs.com/keywords-explorer
A14: 7 | B14: Motorcycle oil guide | C14: motorcycle oil cluster | D14: =SUMIF('Master Keywords'!$B:$B,"*motorcycle oil*",'Master Keywords'!$C:$C) | E14: 0 | F14: Built v2.4.5 | G14: Explain viscosity/spec matching; add product commerce later only when exact application and seller data are verified. | H14: /maintenance/motorcycle-oil | I14: High | J14: Low | K14: =ROUND(0.55*(IF(D14>0,LOG10(D14+1)/LOG10(MAX($D$8:$D$21)+1)*100,35))+0.15*((10-MIN(E14,10))*10)+0.2*IF(I14="High",100,IF(I14="Medium",65,35))+0.1*IF(J14="Low",100,IF(J14="Medium",60,30)),0) | L14: v2.4.5 | M14: Commercial KD0 cluster with affiliate potential. | N14: https://ahrefs.com/keywords-explorer
A15: 8 | B15: Motorcycle coolant guide | C15: coolant cluster | D15: =SUMIF('Master Keywords'!$B:$B,"*coolant*",'Master Keywords'!$C:$C) | E15: 0 | F15: Built v2.4.5 | G15: Own generic coolant intent but always defer chemistry and interval to the exact manual. | H15: /maintenance/coolant-for-motorcycle | I15: Medium | J15: Low | K15: =ROUND(0.55*(IF(D15>0,LOG10(D15+1)/LOG10(MAX($D$8:$D$21)+1)*100,35))+0.15*((10-MIN(E15,10))*10)+0.2*IF(I15="High",100,IF(I15="Medium",65,35))+0.1*IF(J15="Low",100,IF(J15="Medium",60,30)),0) | L15: v2.4.5 | M15: Simple evergreen KD0 win backed by official after-sales sources. | N15: https://ahrefs.com/keywords-explorer
A16: 9 | B16: Motorcycle sprocket guide | C16: sprocket cluster | D16: =SUMIF('Master Keywords'!$B:$B,"*sprocket*",'Master Keywords'!$C:$C) | E16: 1 | F16: Built v2.4.5 | G16: Cover chain/sprocket wear and gearing basics; avoid fitment claims until exact part data exists. | H16: /maintenance/sprocket-motorcycle | I16: Medium | J16: Low | K16: =ROUND(0.55*(IF(D16>0,LOG10(D16+1)/LOG10(MAX($D$8:$D$21)+1)*100,35))+0.15*((10-MIN(E16,10))*10)+0.2*IF(I16="High",100,IF(I16="Medium",65,35))+0.1*IF(J16="Low",100,IF(J16="Medium",60,30)),0) | L16: v2.4.5 | M16: Commercial low-KD intent outside the scooter-only audience. | N16: https://ahrefs.com/keywords-explorer
A17: 10 | B17: Scooter CVT guide | C17: cvt motorcycle | D17: =SUMIF('Master Keywords'!$B:$B,"cvt motorcycle",'Master Keywords'!$C:$C) | E17: 0 | F17: Built v2.4.5 | G17: Use the generic page to explain V-belt/rollers/clutch, then link exact model schedules as they become available. | H17: /maintenance/cvt-motorcycle | I17: Medium | J17: Low | K17: =ROUND(0.55*(IF(D17>0,LOG10(D17+1)/LOG10(MAX($D$8:$D$21)+1)*100,35))+0.15*((10-MIN(E17,10))*10)+0.2*IF(I17="High",100,IF(I17="Medium",65,35))+0.1*IF(J17="Low",100,IF(J17="Medium",60,30)),0) | L17: v2.4.5 | M17: Strong fit with MotoIndex scooter audience and future parts commerce. | N17: https://ahrefs.com/keywords-explorer
A18: 11 | B18: Exact maintenance schedules for top scooters | C18: NMAX / Aerox / ADV / Fazzio maintenance | D18: 0 | E18: 0 | F18: Only Click 160 + PCX 160 exact | G18: Parse official owner manuals for the highest-traffic scooter models; index a maintenance page only when intervals are source-backed. | H18: /motorcycles/{make}/{model}/maintenance | I18: High | J18: Medium | K18: =ROUND(0.55*(IF(D18>0,LOG10(D18+1)/LOG10(MAX($D$8:$D$21)+1)*100,35))+0.15*((10-MIN(E18,10))*10)+0.2*IF(I18="High",100,IF(I18="Medium",65,35))+0.1*IF(J18="Low",100,IF(J18="Medium",60,30)),0) | L18: v2.4.6 | M18: Improves topical authority and conversion without creating thin generic pages. | N18: https://ahrefs.com/keywords-explorer
A19: 12 | B19: Helmet / repair / tire shop local directory | C19: shop near me cluster | D19: =SUMIF('Master Keywords'!$B:$B,"*shop near me*",'Master Keywords'!$C:$C) | E19: 0 | F19: Not built — data required | G19: Build only after verified business records exist. No generated city/category pages without enough real businesses. | H19: /shops/{city}/{category}/ | I19: High | J19: High | K19: =ROUND(0.55*(IF(D19>0,LOG10(D19+1)/LOG10(MAX($D$8:$D$21)+1)*100,35))+0.15*((10-MIN(E19,10))*10)+0.2*IF(I19="High",100,IF(I19="Medium",65,35))+0.1*IF(J19="Low",100,IF(J19="Medium",60,30)),0) | L19: Later | M19: Local intent is valuable but quality depends on real business verification. | N19: https://ahrefs.com/keywords-explorer
A20: 13 | B20: Gloves, jacket and rain-gear commerce | C20: motorcycle gloves / jacket / raincoat | D20: =SUMIF('Master Keywords'!$B:$B,"motorcycle gloves",'Master Keywords'!$C:$C)+SUMIF('Master Keywords'!$B:$B,"motorcycle jacket",'Master Keywords'!$C:$C)+SUMIF('Master Keywords'!$B:$B,"raincoat for motorcycle",'Master Keywords'!$C:$C) | E20: 2 | F20: Category shell only | G20: Add real checked products, sizing/fit notes and affiliate mapping before making category pages deeper. | H20: /accessories/{category}/ | I20: High | J20: Medium | K20: =ROUND(0.55*(IF(D20>0,LOG10(D20+1)/LOG10(MAX($D$8:$D$21)+1)*100,35))+0.15*((10-MIN(E20,10))*10)+0.2*IF(I20="High",100,IF(I20="Medium",65,35))+0.1*IF(J20="Low",100,IF(J20="Medium",60,30)),0) | L20: v2.4.6 | M20: Commercial accessory demand, but current product depth is weaker than helmets/top boxes. | N20: https://ahrefs.com/keywords-explorer
A21: 14 | B21: Used/repo trust layer | C21: repo motorcycle + second-hand terms | D21: 0 | E21: 0 | F21: Shipped v2.4.3 | G21: Maintain source freshness; do not prioritize marketplace scale until the main SEO foundation is ranking. | H21: /used-motorcycles/repo | I21: Medium | J21: Medium | K21: =ROUND(0.55*(IF(D21>0,LOG10(D21+1)/LOG10(MAX($D$8:$D$21)+1)*100,35))+0.15*((10-MIN(E21,10))*10)+0.2*IF(I21="High",100,IF(I21="Medium",65,35))+0.1*IF(J21="Low",100,IF(J21="Medium",60,30)),0) | L21: Monitor | M21: Strategically useful, but lower raw search volume than maintenance and ownership opportunities. | N21: https://ahrefs.com/keywords-explorer
A24: Execution plan
A25: Now — v2.4.5 | B25: Ship the maintenance/parts hub, registration refresh and helmet-brand comparison improvements. These are public-site changes with no new backend dependency.
A26: Next — v2.4.6 | B26: Parse exact maintenance schedules for NMAX/Aerox/ADV/Fazzio and deepen gloves/jacket/rain-gear commerce with real product data.
A27: Then | B27: Use Search Console to promote pages with impressions but weak CTR; update titles/snippets before creating more pages.
A28: Later | B28: Build local shop/dealer discovery only when there are enough verified business records. Keep unrestricted used listings and automation lower priority for now.
A30: SEO guardrails
A31: 1. | B31: Do not create keyword-alias pages when one canonical page already satisfies the intent.
A32: 2. | B32: Do not index model maintenance or fitment pages without exact source-backed data for the generation/year.
A33: 3. | B33: Do not publish “best” safety rankings based on helmet brand reputation; compare exact products and verified markings.
A34: 4. | B34: Refresh LTO, insurance, price, fitment and product-source pages on a dated schedule.
A35: 5. | B35: After launch, use Search Console impressions/CTR to reprioritize the roadmap; keyword volume alone is not the success metric.

Sheet Build Plan
A1: What to Build
A3: Layer | B3: What to build | C3: Required structured fields | D3: Primary pages generated | E3: Data source / workflow | F3: Monetization | G3: Priority | H3: Current status (2026-08-26) | I3: Next action
A4: 1. Motorcycle DB | B4: Canonical make/model/generation database | C4: make, model, generation, year, SRP, variants, engine, power, torque, weight, seat height, tank, dimensions, front/rear tire, brakes, battery, oil capacity | D4: /motorcycles/{make}/{model}/, /price/, /specs/, /tire-size/ | E4: Official manufacturer specs + dealer price checks; version records by year | F4: Dealer leads, finance leads, ads | G4: P1 | H4: Shipped core catalog | I4: Maintain verified models, variants and source freshness.
A5: 2. Price engine | B5: Current SRP + dealer/financing layer | C5: SRP, cash price, dealer price, downpayment, term, monthly payment, last verified | D5: /{model}/price/, /{model}/installment/ | E5: Manufacturer SRP + dealer feeds/manual verification | F5: Finance/dealer leads | G5: P1 | H5: Shipped public price layer | I5: Improve conversion and freshness; live dealer ingestion can wait.
A6: 3. Comparison engine | B6: Pairwise model comparisons | C6: normalized specs, price, performance, utility, fuel economy, seat height, storage | D6: /compare/{model-a}-vs-{model-b}/ | E6: Generated from motorcycle DB + editorial verdict blocks | F6: Dealer leads, ads | G6: P1 | H6: Shipped core comparisons | I6: Add only high-demand pairs and avoid thin pair permutations.
A7: 4. Tire fitment DB | B7: Stock and compatible tire sizes by model | C7: front size, rear size, rim, pressure, alternate sizes, tire type, compatibility notes | D7: /{model}/tire-size/, /tires/{size}/ | E7: Owner manuals + manufacturer specs + tire-maker fitment data | F7: Tire affiliate, local tire-shop leads | G7: P1 | H7: Shipped high-volume fitment tranche | I7: Expand exact fitment when manufacturer/tire-maker evidence exists.
A8: 5. Helmet catalog | B8: Helmet brand/model/price/certification database | C8: brand, model, type, price, sizes, weight, shell, certification, visor, intercom-ready | D8: /gear/helmets/{brand}/, /{brand}/{model}/ | E8: Brand/distributor catalogs + retailer price checks | F8: Affiliate/ecommerce/sponsors | G8: P1 | H8: Shipped broad helmet catalog | I8: Deepen checked models; optimize helmet-brand comparison intent.
A9: 6. Accessory compatibility | B9: Accessory × motorcycle model graph | C9: accessory type, brand, model, compatible bikes, bracket/adaptor, price, dimensions | D9: /{model}/accessories/, /{model}/top-box/, /accessories/{type}/ | E9: Manufacturer fitment lists + retailer catalogs + manual QA | F9: Affiliate/ecommerce | G9: P2 | H9: Partial | I9: Keep top-box verified fitment; expand gloves/jackets/rain gear only with real product data.
A10: 7. Maintenance DB | B10: Intervals and consumables by model | C10: oil grade/capacity, spark plug, battery code, coolant, CVT belt, brake pad, service interval | D10: /{model}/maintenance/, /{model}/oil-capacity/, /{model}/battery/ | E10: Owner/service manuals; mark source + last verified | F10: Parts affiliate, service leads | G10: P2 | H10: Current SEO focus | I10: Build evergreen maintenance/parts topics and expand exact model schedules.
A11: 8. LTO/ownership hub | B11: Registration, renewal, transfer, penalties, plates | C11: requirements, fees, forms, deadlines, official link, last verified | D11: /ownership/registration/, /ownership/renewal/, /ownership/transfer/ | E11: Official LTO / government sources only; freshness checks | F11: Insurance leads, ads | G11: P2 | H11: Shipped core ownership guides | I11: Maintain LTO/Insurance Commission freshness; improve registration query coverage.
A12: 9. Local directory | B12: Dealers, repair shops, tire/helmet shops | C12: business, city, address, hours, phone, brands/services, coordinates | D12: /shops/{city}/{category}/, /dealers/{brand}/{city}/ | E12: Business verification + claimed listings | F12: Lead gen / sponsored listings | G12: P3 | H12: Not built | I12: Only build with verified local-business data; do not generate thin city pages.
A13: 10. Editorial layer | B13: Reviews, best-ofs, explainers, new launches | C13: author, test methodology, photos, pros/cons, linked entities | D13: /guides/, /reviews/, /news/ | E13: Human editorial; link into database entities | F13: Sponsors, affiliate, ads | G13: P2

Sheet Page Templates
A1: Core Page Templates
A3: Template | B3: URL pattern | C3: Must-have modules | D3: Structured data needed | E3: Internal links | F3: Do not publish unless
A4: Model hub | B4: /motorcycles/{make}/{model}/ | C4: Current price, variants, key specs, financing CTA, tire size, related accessories, comparisons | D4: Motorcycle entity record + update date | E4: Price, specs, tire, accessories, comparisons, dealers | F4: Core fields are complete and source is recorded
A5: Price page | B5: /motorcycles/{make}/{model}/price/ | C5: SRP, price by variant, dealer pricing notes, installment examples, price history | D5: Price records by date/variant | E5: Model hub, financing, dealers, comparisons | F5: Price has been verified recently
A6: Tire fitment | B6: /motorcycles/{make}/{model}/tire-size/ | C6: Front/rear stock size, pressure, alternatives, compatible tires, warnings | D6: Fitment record by generation/year | E6: Model hub, tire brands, maintenance | F6: Generation/year fitment is known
A7: Helmet brand hub | B7: /gear/helmets/{brand}/ | C7: Price range, models, types, certification, best sellers, where to buy | D7: Helmet catalog | E7: Helmet models, best-of guides, shops | F7: At least several real products/models exist
A8: Accessory compatibility | B8: /motorcycles/{make}/{model}/{accessory}/ | C8: Compatible products, fitment notes, bracket requirements, price, pros/cons | D8: Compatibility graph | E8: Model, accessory category, product pages | F8: Compatibility is explicitly verified
A9: Maintenance | B9: /motorcycles/{make}/{model}/maintenance/ | C9: Intervals, oil, battery, plug, filters, brakes, CVT/chain, checklist | D9: Service specs + intervals | E9: Parts guides, model hub, local service | F9: Manual/source and generation are identified
A10: Comparison | B10: /compare/{a}-vs-{b}/ | C10: Price/spec table, practical differences, best for whom, related alternatives | D10: Normalized model records | E10: Both model hubs, financing, reviews | F10: Both model records are complete
A11: LTO process | B11: /ownership/{process}/ | C11: Requirements, fees, steps, official links, FAQ, last verified | D11: Government process record | E11: Related fees, insurance, model ownership guides | F11: Official source and verification date are shown

Sheet README
A1: PH Motorcycle SEO Research — 2026-08-24
A3: Scope | B3: Philippines keywords collected from Ahrefs Keywords Explorer during this chat. Master sheet keeps numeric KD 0–10 only.
A4: Volume | B4: PH Volume/mo is Ahrefs estimated monthly search volume, not guaranteed visits.
A5: KD | B5: Keyword Difficulty is a directional link-competition metric. Validate SERPs before publishing or forecasting traffic.
A6: Opportunity Score | B6: Formula combines log-scaled search volume, lower KD, and commercial intent. It is a prioritization heuristic, not an Ahrefs metric.
A7: pSEO rule | B7: Do not index thin permutations. A generated page should answer a distinct user need with verified structured data.
A8: Freshness | B8: Price, financing, LTO, insurance, and compatibility pages need last-verified dates and a refresh queue.
A9: Best first wedge | B9: Start with 30–50 high-volume scooter/motorcycle models + tire fitment + price/financing + 10–15 helmet brands.
A10: Source | B10: https://ahrefs.com/keywords-explorer
A12: Volume roadmap | B12: See “Volume-First Roadmap” for the top 20 build targets, current MotoIndex status, phased execution plan, missing helmet-brand gaps, and used-market placement based on search volume.
A14: Current roadmap | B14: See “SEO Roadmap v2.4.5” for the post-build priority list. The older “Volume-First Roadmap” remains as the original baseline and now shows shipped status for its top 20 targets.
